pms_model_manager/__init__.py
pms_model_manager/_cli.py
pms_model_manager/_const.py
pms_model_manager/_mlflow_model.py
pms_model_manager/_mlflow_model_collection.py
pms_model_manager/_model_manager.py
pms_model_manager/_utils.py
pms_model_manager/onnx_utility/__init__.py
pms_model_manager/onnx_utility/_const.py
pms_model_manager/onnx_utility/_extractor.py
pms_model_manager/onnx_utility/_onnx_graph_info.py
pms_model_manager/onnx_utility/_onnx_model_info.py
pms_model_manager-1.3.2.dist-info/METADATA
pms_model_manager-1.3.2.dist-info/WHEEL
pms_model_manager-1.3.2.dist-info/entry_points.txt
pms_model_manager-1.3.2.dist-info/RECORD
