Metadata-Version: 2.3
Name: pms-model-manager
Version: 1.3.2
Summary: lib for pms
Author: HyeongSeok Kim
Author-email: tiryul@gmail.com
Requires-Python: >=3.10,<4.0
Classifier: Programming Language :: Python :: 3
Classifier: Programming Language :: Python :: 3.10
Classifier: Programming Language :: Python :: 3.11
Classifier: Programming Language :: Python :: 3.12
Classifier: Programming Language :: Python :: 3.13
Requires-Dist: boto3
Requires-Dist: loguru
Requires-Dist: mlflow (>=2.11,<2.20)
Requires-Dist: onnx
Requires-Dist: pytz
Requires-Dist: typer
